snac/__init__.py
snac/attention.py
snac/layers.py
snac/snac.py
snac/vq.py
snac-1.2.1.dist-info/LICENSE
snac-1.2.1.dist-info/METADATA
snac-1.2.1.dist-info/WHEEL
snac-1.2.1.dist-info/top_level.txt
snac-1.2.1.dist-info/RECORD
