Metadata-Version: 2.1
Name: snac
Version: 1.2.1
Summary: Multi-Scale Neural Audio Codec
Home-page: https://github.com/hubertsiuzdak/snac
Author: Hubert Siuzdak
Author-email: hubert.siuzdak@gmail.com
License-File: LICENSE
Requires-Dist: torch
Requires-Dist: numpy
Requires-Dist: einops
Requires-Dist: huggingface-hub
